rosdep2/__init__.py
rosdep2/__main__.py
rosdep2/_version.py
rosdep2/cache_tools.py
rosdep2/catkin_packages.py
rosdep2/catkin_support.py
rosdep2/core.py
rosdep2/dependency_graph.py
rosdep2/gbpdistro_support.py
rosdep2/install.py
rosdep2/installers.py
rosdep2/loader.py
rosdep2/lookup.py
rosdep2/main.py
rosdep2/meta.py
rosdep2/model.py
rosdep2/rep3.py
rosdep2/rosdistrohelper.py
rosdep2/rospack.py
rosdep2/rospkg_loader.py
rosdep2/shell_utils.py
rosdep2/sources_list.py
rosdep2/url_utils.py
rosdep2/ament_packages/__init__.py
rosdep2/ament_packages/constants.py
rosdep2/ament_packages/packages.py
rosdep2/ament_packages/resources.py
rosdep2/ament_packages/search_paths.py
rosdep2/platforms/__init__.py
rosdep2/platforms/alpine.py
rosdep2/platforms/arch.py
rosdep2/platforms/cygwin.py
rosdep2/platforms/debian.py
rosdep2/platforms/freebsd.py
rosdep2/platforms/gem.py
rosdep2/platforms/gentoo.py
rosdep2/platforms/nix.py
rosdep2/platforms/npm.py
rosdep2/platforms/openembedded.py
rosdep2/platforms/opensuse.py
rosdep2/platforms/osx.py
rosdep2/platforms/pip.py
rosdep2/platforms/redhat.py
rosdep2/platforms/slackware.py
rosdep2/platforms/source.py
rosdep2-0.26.0.1.dist-info/licenses/LICENSE
rosdep2-0.26.0.1.dist-info/METADATA
rosdep2-0.26.0.1.dist-info/WHEEL
rosdep2-0.26.0.1.dist-info/entry_points.txt
rosdep2-0.26.0.1.dist-info/top_level.txt
rosdep2-0.26.0.1.dist-info/RECORD
