Metadata-Version: 2.4
Name: rosdep2
Version: 0.26.0.1
Summary: rosdep - enhanced with lovely quality of life improvements
Home-page: http://wiki.ros.org/rosdep
Author: Tully Foote, Ken Conley
Author-email: Tully Foote <tfoote@osrfoundation.org>
Maintainer: ROS Infrastructure Team
License-Expression: BSD-2-Clause
Project-URL: Homepage, https://github.com/krisl/rosdep
Classifier: Programming Language :: Python
Requires-Python: >=3.7
License-File: LICENSE
Requires-Dist: PyYAML>=3.1
Requires-Dist: importlib-metadata; python_version < "3.8"
Requires-Dist: catkin-pkg
Requires-Dist: rospkg>=1.4.0
Requires-Dist: rosdistro>=0.7.5
Requires-Dist: packaging
Provides-Extra: test
Requires-Dist: flake8; extra == "test"
Requires-Dist: flake8-builtins; extra == "test"
Requires-Dist: flake8-comprehensions; extra == "test"
Requires-Dist: flake8-quotes; extra == "test"
Requires-Dist: pytest; extra == "test"
Dynamic: author
Dynamic: home-page
Dynamic: license-file
Dynamic: maintainer
